execute_sincronization.py
main.py
pr_async_db.py
pr_repository_async.py
softseguros/__init__.py
softseguros/api_libertador/__init__.py
softseguros/api_libertador/api.py
softseguros/api_libertador/codes_status_api.py
softseguros/api_libertador/custom_execptions_api.py
softseguros/api_libertador/execute_load_to_db.py
softseguros/api_libertador/models_request.py
softseguros/api_libertador/models_response.py
softseguros/api_softin/fetch_softin.py
softseguros/api_softseguros/api_softseguros.py
softseguros/api_softseguros/create_customers_libertador.py
softseguros/api_softseguros/create_customers_softin.py
softseguros/api_softseguros/create_prospectsfrom_in_crm_softseguros.py
softseguros/api_softseguros/models_requests.py
softseguros/api_softseguros/models_response.py
softseguros/config/logging_config.py
softseguros/config/settings.py
softseguros/database/__init__.py
softseguros/database/config_db.py
softseguros/database/models/__init__.py
softseguros/database/models/models.py
softseguros/database/repositories/__init__.py
softseguros/database/repositories/libertadors.py
softseguros/database/repositories/softin.py
softseguros/database/repositories/softseguros.py
softseguros/notifier/notificaciones.py
lagencia_prospects_softseguros-0.1.18.dist-info/METADATA
lagencia_prospects_softseguros-0.1.18.dist-info/WHEEL
lagencia_prospects_softseguros-0.1.18.dist-info/top_level.txt
lagencia_prospects_softseguros-0.1.18.dist-info/RECORD
