Metadata-Version: 2.4
Name: LAgencia-prospects-softseguros
Version: 0.1.18
Summary: Add your description here
Requires-Python: >=3.11
Requires-Dist: httpx>=0.28.1
Requires-Dist: loguru>=0.7.3
Requires-Dist: nameparser>=1.1.3
Requires-Dist: pydantic==2.8.2
Requires-Dist: pydantic-settings==2.11.0
Requires-Dist: pymssql>=2.3.9
Requires-Dist: pymysql==1.1.2
Requires-Dist: python-dotenv>=1.1.1
Requires-Dist: requests>=2.32.5
Requires-Dist: sqlalchemy==1.4.53
